beeai_framework/__init__.py
beeai_framework/adapters/__init__.py
beeai_framework/adapters/a2a/__init__.py
beeai_framework/adapters/a2a/agents/__init__.py
beeai_framework/adapters/a2a/agents/_utils.py
beeai_framework/adapters/a2a/agents/agent.py
beeai_framework/adapters/a2a/agents/events.py
beeai_framework/adapters/a2a/agents/types.py
beeai_framework/adapters/a2a/serve/__init__.py
beeai_framework/adapters/a2a/serve/context.py
beeai_framework/adapters/a2a/serve/executors/__init__.py
beeai_framework/adapters/a2a/serve/executors/base_a2a_agent_executor.py
beeai_framework/adapters/a2a/serve/executors/base_a2a_executor.py
beeai_framework/adapters/a2a/serve/executors/react_agent_executor.py
beeai_framework/adapters/a2a/serve/executors/tool_calling_agent_executor.py
beeai_framework/adapters/a2a/serve/server.py
beeai_framework/adapters/acp/__init__.py
beeai_framework/adapters/acp/agents/__init__.py
beeai_framework/adapters/acp/agents/agent.py
beeai_framework/adapters/acp/agents/events.py
beeai_framework/adapters/acp/agents/types.py
beeai_framework/adapters/acp/serve/__init__.py
beeai_framework/adapters/acp/serve/_utils.py
beeai_framework/adapters/acp/serve/agent.py
beeai_framework/adapters/acp/serve/io.py
beeai_framework/adapters/acp/serve/server.py
beeai_framework/adapters/agentstack/__init__.py
beeai_framework/adapters/agentstack/agents/__init__.py
beeai_framework/adapters/agentstack/agents/agent.py
beeai_framework/adapters/agentstack/agents/events.py
beeai_framework/adapters/agentstack/agents/types.py
beeai_framework/adapters/agentstack/backend/__init__.py
beeai_framework/adapters/agentstack/backend/chat.py
beeai_framework/adapters/agentstack/backend/embedding.py
beeai_framework/adapters/agentstack/backend/vector_store.py
beeai_framework/adapters/agentstack/context.py
beeai_framework/adapters/agentstack/serve/__init__.py
beeai_framework/adapters/agentstack/serve/_dummy_context_store.py
beeai_framework/adapters/agentstack/serve/factories.py
beeai_framework-0.1.76.dist-info/LICENSE
beeai_framework-0.1.76.dist-info/METADATA
beeai_framework-0.1.76.dist-info/WHEEL
beeai_framework-0.1.76.dist-info/entry_points.txt
beeai_framework-0.1.76.dist-info/RECORD
