Metadata-Version: 2.3
Name: beeai-framework
Version: 0.1.76
Summary: 
License: Apache-2.0
Author: IBM Corp.
Maintainer: Fred Araujo
Maintainer-email: frederico.araujo@ibm.com
Requires-Python: >=3.11,<4.0
Classifier: License :: OSI Approved :: Apache Software License
Classifier: Programming Language :: Python :: 3
Classifier: Programming Language :: Python :: 3.11
Classifier: Programming Language :: Python :: 3.12
Classifier: Programming Language :: Python :: 3.13
Provides-Extra: a2a
Provides-Extra: acp
Provides-Extra: agentstack
Provides-Extra: all
Provides-Extra: bedrock
Provides-Extra: beeai-platform
Provides-Extra: duckduckgo
Provides-Extra: huggingface
Provides-Extra: langchain
Provides-Extra: llama-index
Provides-Extra: mcp
Provides-Extra: rag
Provides-Extra: search
Provides-Extra: transformers
Provides-Extra: vertexai
Provides-Extra: watsonx-orchestrate
Provides-Extra: wikipedia
Requires-Dist: a2a-sdk[grpc,http-server,telemetry] (>=0.3.9,<0.4.0) ; extra == "beeai-platform" or extra == "agentstack" or extra == "a2a" or extra == "all"
Requires-Dist: acp-sdk (>=1.0.3,<2.0.0) ; extra == "acp" or extra == "all"
Requires-Dist: agentstack-sdk (==0.4.3) ; extra == "beeai-platform" or extra == "agentstack" or extra == "all"
Requires-Dist: aiofiles (>=24.1.0,<25.0.0)
Requires-Dist: boto3 (>=1.37.5,<2.0.0) ; extra == "bedrock" or extra == "all"
Requires-Dist: cachetools (>=5.5.2)
Requires-Dist: chevron (>=0.14.0,<0.15.0)
Requires-Dist: ddgs (>=9.10.0,<10.0.0) ; extra == "search" or extra == "duckduckgo" or extra == "all"
Requires-Dist: deprecated (>=1.2.18,<2.0.0)
Requires-Dist: fastapi (>=0.116.0,<0.117.0) ; extra == "watsonx-orchestrate" or extra == "all"
Requires-Dist: google-auth (>=2.14,<3.0.0) ; extra == "vertexai" or extra == "all"
Requires-Dist: grpcio-health-checking ; extra == "a2a" or extra == "all"
Requires-Dist: json-repair (>=0.52.5,<0.53.0)
Requires-Dist: jsonref (>=1.1.0,<2.0.0)
Requires-Dist: langchain-community (<1.0.0) ; extra == "langchain" or extra == "rag" or extra == "all"
Requires-Dist: langchain-core (<1.0.0) ; extra == "langchain" or extra == "rag" or extra == "all"
Requires-Dist: langchain-ollama (<1.0.0) ; extra == "langchain" or extra == "rag" or extra == "all"
Requires-Dist: langgraph (<1.0.0) ; extra == "langchain" or extra == "rag" or extra == "all"
Requires-Dist: litellm (>=1.80.11,<2.0.0)
Requires-Dist: llama-index-core (>=0.14.0,<0.15.0) ; extra == "llama-index" or extra == "rag"
Requires-Dist: markdown (>=3.8.2,<4.0.0) ; extra == "rag"
Requires-Dist: mcp (>=1.23.0,<2.0.0) ; extra == "mcp" or extra == "all"
Requires-Dist: outlines (>=1.2.4,<2.0.0) ; (python_version >= "3.11" and python_version < "3.13") and (extra == "transformers" or extra == "all")
Requires-Dist: peft (>=0.17.1,<0.18.0) ; extra == "transformers" or extra == "all"
Requires-Dist: pydantic (>=2.11.10,<3.0.0)
Requires-Dist: pydantic-settings (>=2.11.0,<3.0.0)
Requires-Dist: requests (>=2.32,<3.0)
Requires-Dist: torch (==2.2.2) ; (sys_platform == "darwin" and platform_machine == "x86_64") and (extra == "transformers" or extra == "all")
Requires-Dist: torch (==2.7.1) ; (sys_platform != "darwin") and (extra == "transformers" or extra == "all")
Requires-Dist: torch (>=2.4.1) ; (sys_platform == "darwin" and platform_machine == "arm64") and (extra == "transformers" or extra == "all")
Requires-Dist: transformers (>=4.49.0) ; (sys_platform != "darwin") and (extra == "transformers" or extra == "huggingface" or extra == "all")
Requires-Dist: transformers (>=4.49.0) ; (sys_platform == "darwin" and platform_machine == "arm64") and (extra == "transformers" or extra == "huggingface" or extra == "all")
Requires-Dist: transformers (>=4.49.0,<=4.51.3) ; (sys_platform == "darwin" and platform_machine == "x86_64") and (extra == "transformers" or extra == "huggingface" or extra == "all")
Requires-Dist: types-grpcio ; extra == "a2a"
Requires-Dist: types-grpcio-health-checking ; extra == "a2a"
Requires-Dist: types-grpcio-reflection ; extra == "a2a"
Requires-Dist: unstructured (>=0.17.2,<0.18.0) ; extra == "rag"
Requires-Dist: uvicorn (>=0.37.0,<0.38.0) ; extra == "acp" or extra == "beeai-platform" or extra == "agentstack" or extra == "a2a" or extra == "watsonx-orchestrate" or extra == "all"
Requires-Dist: wikipedia-api (>=0.8.1,<0.9.0) ; extra == "search" or extra == "wikipedia" or extra == "all"
Project-URL: Documentation, https://i-am-bee.github.io/beeai-framework/#/python/
Project-URL: Homepage, https://framework.beeai.dev/
Project-URL: Repository, https://github.com/i-am-bee/beeai-framework
